nervos/__init__.py
nervos/dataloader/__init__.py
nervos/dataloader/circles.py
nervos/dataloader/iris.py
nervos/dataloader/loader.py
nervos/dataloader/mnist.py
nervos/examples/__init__.py
nervos/examples/neuron_spiking.py
nervos/utils/__init__.py
nervos/utils/common.py
nervos/utils/layer.py
nervos/utils/module.py
nervos/utils/neuron.py
nervos/utils/parameters.py
nervos-0.0.5.dist-info/licenses/COPYING
nervos-0.0.5.dist-info/METADATA
nervos-0.0.5.dist-info/WHEEL
nervos-0.0.5.dist-info/top_level.txt
nervos-0.0.5.dist-info/RECORD
